encryption/__init__.py
encryption/encrypt_code.py
encryption/license_utils.py
encryptKit-0.2.dist-info/LICENSE
encryptKit-0.2.dist-info/METADATA
encryptKit-0.2.dist-info/WHEEL
encryptKit-0.2.dist-info/entry_points.txt
encryptKit-0.2.dist-info/top_level.txt
encryptKit-0.2.dist-info/RECORD
