Metadata-Version: 2.1
Name: encryptKit
Version: 0.2
Summary: python project encryption
Home-page: https://github.com/fushengwuyu/pyencryption
Author: sunshine
Author-email: 
License: UNKNOWN
Platform: UNKNOWN
Classifier: Programming Language :: Python :: 3
Classifier: License :: OSI Approved :: MIT License
Classifier: Operating System :: OS Independent
License-File: LICENSE
Requires-Dist: pydantic
Requires-Dist: pycryptodome
Requires-Dist: M2Crypto
Requires-Dist: Cython
